textree/TestTexTree.py
textree/__init__.py
textree/test_import.py
textree/textree.py
textree/py2/TestTexTree.py
textree/py2/__init__.py
textree/py2/example.py
textree/py2/textree.py
textree/py3/TestTexTree.py
textree/py3/__init__.py
textree/py3/example.py
textree/py3/textree.py
textree-0.0.1.dist-info/LICENSE.txt
textree-0.0.1.dist-info/METADATA
textree-0.0.1.dist-info/WHEEL
textree-0.0.1.dist-info/top_level.txt
textree-0.0.1.dist-info/RECORD
