Metadata-Version: 2.1
Name: textree
Version: 0.0.1
Summary: Create nodes as specified in the tree text.
Home-page: https://github.com/textree/textree
Author: ytyaru
Author-email: pypi1@outlook.jp
License: GNU Affero General Public License Version 3 (AGPL-3.0)
Keywords: tree,text,node,textprocess,texttotree,texttonode,treetotext,treetonode,mapper,ObjectToTextMapper,serializer,deserializer,generator,convertor
Platform: UNKNOWN
Classifier: Development Status :: 3 - Alpha
Classifier: Programming Language :: Python
Classifier: Programming Language :: Python :: 2.7
Classifier: Programming Language :: Python :: 3
Classifier: License :: OSI Approved :: GNU Affero General Public License v3
Classifier: Operating System :: OS Independent
Classifier: Intended Audience :: Developers
Classifier: Topic :: Software Development :: Libraries
Classifier: Topic :: Text Processing
Classifier: Topic :: Utilities
Requires-Python: >=2.7
